test_url_shortener/__init__.py
test_url_shortener/test_url_shortener_api.py
url_shortener/__init__.py
url_shortener/url_shortener_api.py
cocfire_url_shortener_api-0.0.5.dist-info/LICENSE
cocfire_url_shortener_api-0.0.5.dist-info/METADATA
cocfire_url_shortener_api-0.0.5.dist-info/WHEEL
cocfire_url_shortener_api-0.0.5.dist-info/top_level.txt
cocfire_url_shortener_api-0.0.5.dist-info/RECORD
