Metadata-Version: 2.1
Name: cocfire-url-shortener-api
Version: 0.0.5
License-File: LICENSE
Requires-Dist: requests
